odoo/addons/l10n_br_stock_account/README.rst
odoo/addons/l10n_br_stock_account/__init__.py
odoo/addons/l10n_br_stock_account/__manifest__.py
odoo/addons/l10n_br_stock_account/hooks.py
odoo/addons/l10n_br_stock_account/data/l10n_br_stock_account_data.xml
odoo/addons/l10n_br_stock_account/demo/account_journal_demo.xml
odoo/addons/l10n_br_stock_account/demo/company_demo.xml
odoo/addons/l10n_br_stock_account/demo/fiscal_operation_generic.xml
odoo/addons/l10n_br_stock_account/demo/fiscal_operation_simple.xml
odoo/addons/l10n_br_stock_account/demo/l10n_br_stock_account_demo.xml
odoo/addons/l10n_br_stock_account/demo/stock_inventory_demo.xml
odoo/addons/l10n_br_stock_account/i18n/l10n_br_stock_account.pot
odoo/addons/l10n_br_stock_account/i18n/pt_BR.po
odoo/addons/l10n_br_stock_account/models/__init__.py
odoo/addons/l10n_br_stock_account/models/procurement_group.py
odoo/addons/l10n_br_stock_account/models/res_company.py
odoo/addons/l10n_br_stock_account/models/stock_move.py
odoo/addons/l10n_br_stock_account/models/stock_picking.py
odoo/addons/l10n_br_stock_account/models/stock_picking_type.py
odoo/addons/l10n_br_stock_account/models/stock_rule.py
odoo/addons/l10n_br_stock_account/readme/CONFIGURE.rst
odoo/addons/l10n_br_stock_account/readme/CONTRIBUTORS.rst
odoo/addons/l10n_br_stock_account/readme/CREDITS.rst
odoo/addons/l10n_br_stock_account/readme/DESCRIPTION.rst
odoo/addons/l10n_br_stock_account/readme/HISTORY.rst
odoo/addons/l10n_br_stock_account/readme/INSTALL.rst
odoo/addons/l10n_br_stock_account/readme/ROADMAP.rst
odoo/addons/l10n_br_stock_account/readme/USAGE.rst
odoo/addons/l10n_br_stock_account/security/ir.model.access.csv
odoo/addons/l10n_br_stock_account/static/description/icon.png
odoo/addons/l10n_br_stock_account/static/description/index.html
odoo/addons/l10n_br_stock_account/tests/__init__.py
odoo/addons/l10n_br_stock_account/tests/common.py
odoo/addons/l10n_br_stock_account/tests/test_invoicing_picking.py
odoo14_addon_l10n_br_stock_account-14.0.3.12.0.dist-info/METADATA
odoo14_addon_l10n_br_stock_account-14.0.3.12.0.dist-info/WHEEL
odoo14_addon_l10n_br_stock_account-14.0.3.12.0.dist-info/top_level.txt
odoo14_addon_l10n_br_stock_account-14.0.3.12.0.dist-info/RECORD
