Metadata-Version: 2.1
Name: odoo14-addon-l10n_br_stock_account
Version: 14.0.3.12.0
Summary: Invoice from Picking (nota fiscal de remessa) and other WMS overrides
Home-page: https://github.com/OCA/l10n-brazil
Author: Akretion, Odoo Community Association (OCA)
Author-email: support@odoo-community.org
License: AGPL-3
Classifier: Programming Language :: Python
Classifier: Framework :: Odoo
Classifier: Framework :: Odoo :: 14.0
Classifier: License :: OSI Approved :: GNU Affero General Public License v3
Requires-Python: >=3.6
Requires-Dist: odoo14-addon-l10n-br-account
Requires-Dist: odoo14-addon-l10n-br-stock
Requires-Dist: odoo14-addon-stock-picking-invoicing
Requires-Dist: odoo<14.1dev,>=14.0a
